{"version":"0.4","title":"Clean CV Resume","type":"page","content":[{"id":"22d42656","settings":{"stretch_section":"section-stretched","background_background":"classic","background_image":{"id":590,"url":"http:\/\/localhost\/wordpress-lawfirm\/wp-content\/uploads\/unlimited_elements\/guy8.png"},"background_position":"center center","background_attachment":"scroll","background_repeat":"no-repeat","background_size":"cover","background_slideshow_gallery":[{"id":591,"url":"http:\/\/localhost\/wordpress-lawfirm\/wp-content\/uploads\/unlimited_elements\/header-fresh.jpg"}],"background_slideshow_background_size":"cover","background_slideshow_background_position":"center center","background_hover_background":"classic","margin":{"unit":"px","top":"","right":0,"bottom":"","left":0,"isLinked":true},"custom_height":{"unit":"vh","size":130,"sizes":[]},"padding_tablet":{"unit":"px","top":"270","right":"0","bottom":"300","left":"0","isLinked":false},"padding":{"unit":"px","top":"0","right":"0","bottom":"0","left":"0","isLinked":false},"padding_mobile":{"unit":"px","top":"30","right":"0","bottom":"30","left":"0","isLinked":false},"height":"full","content_width":{"unit":"px","size":1170,"sizes":[]},"reverse_order_tablet":"reverse-tablet","reverse_order_mobile":"reverse-mobile","gap":"no","structure":"20"},"elements":[{"id":"325860ad","settings":{"_column_size":50,"_inline_size":38,"padding":{"unit":"px","top":"30","right":"30","bottom":"30","left":"30","isLinked":true},"_inline_size_mobile":70,"padding_tablet":{"unit":"px","top":"20","right":"20","bottom":"20","left":"20","isLinked":true}},"elements":[{"id":"7e51d1c2","settings":{"title":"I am \nPhillip Morris\nfrom NYC.","size":"xxl","header_size":"span","align":"left","title_color":"#000000","typography_typography":"custom","typography_font_weight":"400","_padding":{"unit":"%","top":"0","right":"0","bottom":"0","left":"0","isLinked":false},"_animation":"slideInLeft","typography_font_size_mobile":{"unit":"px","size":42,"sizes":[]},"_padding_tablet":{"unit":"px","top":"0","right":"0","bottom":"0","left":"0","isLinked":true}},"elements":[],"isInner":false,"widgetType":"heading","elType":"widget"},{"id":"3475dbfb","settings":{"width":{"unit":"%","size":5,"sizes":[]},"text":"Divider","color":"#A4BAD3","weight":{"unit":"px","size":5,"sizes":[]},"gap":{"unit":"px","size":10,"sizes":[]},"_margin":{"unit":"px","top":"0","right":"0","bottom":"0","left":"0","isLinked":false},"_padding":{"unit":"%","top":"0","right":"0","bottom":"0","left":"0","isLinked":false},"_animation":"slideInLeft","width_mobile":{"unit":"px","size":30,"sizes":[]}},"elements":[],"isInner":false,"widgetType":"divider","elType":"widget"},{"id":"3f620db8","settings":{"editor":"<p>I\u2019m a digital UX \/ UI designer living in United States. I have been playing around with computers since the days of the Macintosh Classic.<\/p>","text_color":"#000000","_animation":"slideInLeft","_padding":{"unit":"%","top":"0","right":"0","bottom":"0","left":"0","isLinked":false},"_padding_tablet":{"unit":"px","top":"0","right":"0","bottom":"0","left":"0","isLinked":true}},"elements":[],"isInner":false,"widgetType":"text-editor","elType":"widget"},{"id":"5a4f9bd9","settings":{"text":"Contact Me","typography_typography":"custom","typography_font_size":{"unit":"px","size":18,"sizes":[]},"button_text_color":"#C1DBF8","background_color":"#000000","text_padding":{"unit":"px","top":"21","right":"26","bottom":"21","left":"26","isLinked":false},"_animation":"slideInLeft","_animation_delay":500,"_border_radius":{"unit":"px","top":"0","right":"0","bottom":"0","left":"0","isLinked":true},"border_radius":{"unit":"px","top":"0","right":"0","bottom":"0","left":"0","isLinked":true},"button_box_shadow_box_shadow_type":"yes","button_box_shadow_box_shadow":{"horizontal":0,"vertical":0,"blur":10,"spread":0,"color":"rgba(0, 0, 0, 0)"},"_box_shadow_box_shadow_type":"yes","_box_shadow_box_shadow":{"horizontal":0,"vertical":0,"blur":0,"spread":0,"color":"rgba(0,0,0,0.5)"},"link":{"url":"#contact","is_external":"","nofollow":"","custom_attributes":""},"typography_text_transform":"uppercase","_padding":{"unit":"%","top":"0","right":"0","bottom":"0","left":"0","isLinked":false}},"elements":[],"isInner":false,"widgetType":"button","elType":"widget"}],"isInner":false,"elType":"column"},{"id":"7aa223cc","settings":{"_column_size":50,"_inline_size":62},"elements":[],"isInner":false,"elType":"column"}],"isInner":false,"elType":"section"},{"id":"35dbc8c3","settings":{"stretch_section":"section-stretched","content_width":{"unit":"px","size":1170,"sizes":[]},"structure":"40","margin":{"unit":"px","top":"-30","right":0,"bottom":"0","left":0,"isLinked":false},"gap":"no","padding":{"unit":"%","top":"0","right":"0","bottom":"0","left":"0","isLinked":false},"animation":"slideInUp"},"elements":[{"id":"7c4cfe22","settings":{"_column_size":25,"_inline_size":null,"space_between_widgets":0,"text_align":"left","_inline_size_tablet":50},"elements":[{"id":"595010a","settings":{"title":"Development","bg_color":"#ADC5DF","number":"1","icon":{"value":"","library":""},"link_txt":"","link":"","btn_bg":"#ADC5DF","paragraph":"Lorem ipsum dolor sit amet, consectetur adipiscing elit. Cras diam purus, sagittis quis augue et, dictum rhoncus ante.","border_settings":"","ucfont_title__fonts-enabled":"yes","ucfont_title__typography_typography":"custom","ucfont_title__typography_font_weight":"600","ucfont_number__fonts-enabled":"yes","ucfont_number__typography_typography":"custom","ucfont_number__color":"#FFFFFF","ucfont_paragraph__fonts-enabled":"yes","ucfont_paragraph__color":"#FFFFFF","ucfont_title__typography_font_size_tablet":{"unit":"px","size":20,"sizes":[]}},"elements":[],"isInner":false,"widgetType":"ucaddon_blox_icon_button_number_box","elType":"widget"}],"isInner":false,"elType":"column"},{"id":"71193a35","settings":{"_column_size":25,"_inline_size":null,"_inline_size_tablet":50},"elements":[{"id":"343ab153","settings":{"title":"Web Design","bg_color":"#A4BAD3","number":"2","icon":{"value":"","library":""},"link_txt":"","link":"","btn_bg":"#A4BAD3","paragraph":"Lorem ipsum dolor sit amet, consectetur adipiscing elit. Cras diam purus, sagittis quis augue et, dictum rhoncus ante.","border_settings":"","ucfont_title__fonts-enabled":"yes","ucfont_title__typography_typography":"custom","ucfont_title__typography_font_weight":"600","ucfont_number__fonts-enabled":"yes","ucfont_number__typography_typography":"custom","ucfont_number__color":"#FFFFFF","ucfont_paragraph__fonts-enabled":"yes","ucfont_paragraph__color":"#FFFFFF","ucfont_title__typography_font_size_tablet":{"unit":"px","size":20,"sizes":[]}},"elements":[],"isInner":false,"widgetType":"ucaddon_blox_icon_button_number_box","elType":"widget"}],"isInner":false,"elType":"column"},{"id":"392b7ef","settings":{"_column_size":25,"_inline_size":null,"_inline_size_tablet":50},"elements":[{"id":"1ea6314f","settings":{"title":"Application","bg_color":"#9AAFC6","number":"3","icon":{"value":"","library":""},"link_txt":"","link":"","btn_bg":"#9AAFC6","paragraph":"Lorem ipsum dolor sit amet, consectetur adipiscing elit. Cras diam purus, sagittis quis augue et, dictum rhoncus ante.","border_settings":"","ucfont_title__fonts-enabled":"yes","ucfont_title__typography_typography":"custom","ucfont_title__typography_font_weight":"600","ucfont_number__fonts-enabled":"yes","ucfont_number__typography_typography":"custom","ucfont_number__color":"#FFFFFF","ucfont_paragraph__fonts-enabled":"yes","ucfont_paragraph__color":"#FFFFFF","ucfont_title__typography_font_size_tablet":{"unit":"px","size":20,"sizes":[]}},"elements":[],"isInner":false,"widgetType":"ucaddon_blox_icon_button_number_box","elType":"widget"}],"isInner":false,"elType":"column"},{"id":"749963a6","settings":{"_column_size":25,"_inline_size":null,"_inline_size_tablet":50},"elements":[{"id":"25099682","settings":{"title":"Photography","bg_color":"#91A4BA","number":"4","icon":{"value":"","library":""},"link_txt":"","link":"","btn_bg":"#91A4BA","paragraph":"Lorem ipsum dolor sit amet, consectetur adipiscing elit. Cras diam purus, sagittis quis augue et, dictum rhoncus ante.","border_settings":"","ucfont_title__fonts-enabled":"yes","ucfont_title__typography_typography":"custom","ucfont_title__typography_font_weight":"600","ucfont_number__fonts-enabled":"yes","ucfont_number__typography_typography":"custom","ucfont_number__color":"#FFFFFF","ucfont_paragraph__fonts-enabled":"yes","ucfont_paragraph__typography_typography":"custom","ucfont_paragraph__color":"#FFFFFF"},"elements":[],"isInner":false,"widgetType":"ucaddon_blox_icon_button_number_box","elType":"widget"}],"isInner":false,"elType":"column"}],"isInner":false,"elType":"section"},{"id":"312ade14","settings":{"stretch_section":"section-stretched","structure":"20","content_width":{"unit":"px","size":1170,"sizes":[]},"gap":"no","padding":{"unit":"px","top":"100","right":"20","bottom":"0","left":"20","isLinked":false},"animation":"slideInUp"},"elements":[{"id":"7430cdd9","settings":{"_column_size":50,"_inline_size":38,"padding_tablet":{"unit":"px","top":"20","right":"20","bottom":"20","left":"20","isLinked":true}},"elements":[{"id":"1af72c87","settings":{"title":"About Me","size":"large","header_size":"span","title_color":"#000000","typography_typography":"custom","typography_font_weight":"400","_margin":{"unit":"px","top":"0","right":"0","bottom":"0","left":"0","isLinked":false},"_padding":{"unit":"px","top":"0","right":"0","bottom":"0","left":"0","isLinked":false}},"elements":[],"isInner":false,"widgetType":"heading","elType":"widget"},{"id":"27daa43a","settings":{"width":{"unit":"%","size":10,"sizes":[]},"text":"Divider","color":"#A4BAD3","weight":{"unit":"px","size":5,"sizes":[]},"width_mobile":{"unit":"px","size":30,"sizes":[]}},"elements":[],"isInner":false,"widgetType":"divider","elType":"widget"},{"id":"73f5afe0","settings":{"editor":"<p>Lorem ipsum dolor sit amet, consectetur adipiscing elit. Cras rutrum in orci sit amet rutrum. Nunc blandit rhoncus consequat. Donec sodales enim et felis commodo, eget posuere turpis fringilla.<\/p>","typography_typography":"custom","typography_font_size":{"unit":"px","size":14,"sizes":[]},"column_gap":{"unit":"px","size":0,"sizes":[]},"_padding":{"unit":"px","top":"0","right":"100","bottom":"0","left":"0","isLinked":false},"_padding_tablet":{"unit":"px","top":"0","right":"0","bottom":"0","left":"0","isLinked":false}},"elements":[],"isInner":false,"widgetType":"text-editor","elType":"widget"}],"isInner":false,"elType":"column"},{"id":"380b7b8d","settings":{"_column_size":50,"_inline_size":62,"content_position":"top","align":"space-evenly"},"elements":[{"id":"139e25b1","settings":{"structure":"30"},"elements":[{"id":"35d04dc8","settings":{"_column_size":33,"_inline_size":null},"elements":[{"id":"4e3ed51d","settings":{"title_text":"Date of birth","description_text":"March 19, 1988","icon_size":{"unit":"px","size":48,"sizes":[]},"description_typography_typography":"custom","selected_icon":{"value":{"id":594,"url":"http:\/\/localhost\/wordpress-lawfirm\/wp-content\/uploads\/unlimited_elements\/profile.svg"},"library":"svg"},"title_size":"span","primary_color":"#000000","title_color":"#000000","text_align":"left","title_bottom_space":{"unit":"px","size":0,"sizes":[]},"title_typography_typography":"custom","title_typography_font_size":{"unit":"px","size":21,"sizes":[]},"title_typography_font_weight":"400","title_typography_line_height":{"unit":"em","size":0.1,"sizes":[]},"description_typography_font_size":{"unit":"px","size":14,"sizes":[]},"description_typography_line_height":{"unit":"em","size":1.5,"sizes":[]},"description_typography_letter_spacing":{"unit":"px","size":0.5,"sizes":[]},"_padding":{"unit":"px","top":"10","right":"10","bottom":"10","left":"10","isLinked":false}},"elements":[],"isInner":false,"widgetType":"icon-box","elType":"widget"}],"isInner":true,"elType":"column"},{"id":"1483b122","settings":{"_column_size":33,"_inline_size":null},"elements":[{"id":"7738f294","settings":{"title_text":"Address","description_text":"Santa Monica, LA","icon_size":{"unit":"px","size":48,"sizes":[]},"description_typography_typography":"custom","selected_icon":{"value":{"id":582,"url":"http:\/\/localhost\/wordpress-lawfirm\/wp-content\/uploads\/unlimited_elements\/address.svg"},"library":"svg"},"title_size":"span","primary_color":"#000000","title_color":"#000000","text_align":"left","title_bottom_space":{"unit":"px","size":0,"sizes":[]},"title_typography_typography":"custom","title_typography_font_size":{"unit":"px","size":21,"sizes":[]},"title_typography_font_weight":"400","title_typography_line_height":{"unit":"em","size":0.1,"sizes":[]},"description_typography_font_size":{"unit":"px","size":14,"sizes":[]},"description_typography_line_height":{"unit":"em","size":1.5,"sizes":[]},"description_typography_letter_spacing":{"unit":"px","size":0.5,"sizes":[]},"_padding":{"unit":"px","top":"10","right":"10","bottom":"10","left":"10","isLinked":false}},"elements":[],"isInner":false,"widgetType":"icon-box","elType":"widget"}],"isInner":true,"elType":"column"},{"id":"685f9a9b","settings":{"_column_size":33,"_inline_size":null},"elements":[{"id":"784b7565","settings":{"title_text":"Email","description_text":"philip@gmail.com","icon_size":{"unit":"px","size":48,"sizes":[]},"description_typography_typography":"custom","selected_icon":{"value":{"id":589,"url":"http:\/\/localhost\/wordpress-lawfirm\/wp-content\/uploads\/unlimited_elements\/email.svg"},"library":"svg"},"title_size":"span","primary_color":"#000000","title_color":"#000000","text_align":"left","title_bottom_space":{"unit":"px","size":0,"sizes":[]},"title_typography_typography":"custom","title_typography_font_size":{"unit":"px","size":21,"sizes":[]},"title_typography_font_weight":"400","title_typography_line_height":{"unit":"em","size":0.1,"sizes":[]},"description_typography_font_size":{"unit":"px","size":14,"sizes":[]},"description_typography_line_height":{"unit":"em","size":1.5,"sizes":[]},"description_typography_letter_spacing":{"unit":"px","size":0.5,"sizes":[]},"_padding":{"unit":"px","top":"10","right":"10","bottom":"10","left":"10","isLinked":false}},"elements":[],"isInner":false,"widgetType":"icon-box","elType":"widget"}],"isInner":true,"elType":"column"}],"isInner":true,"elType":"section"},{"id":"5fa68e5d","settings":{"structure":"30"},"elements":[{"id":"4d3fff8e","settings":{"_column_size":33,"_inline_size":null},"elements":[{"id":"47c3eb54","settings":{"title_text":"Phone","description_text":"+ 123 456 789 456","icon_size":{"unit":"px","size":48,"sizes":[]},"description_typography_typography":"custom","selected_icon":{"value":{"id":593,"url":"http:\/\/localhost\/wordpress-lawfirm\/wp-content\/uploads\/unlimited_elements\/phone.svg"},"library":"svg"},"title_size":"span","primary_color":"#000000","title_color":"#000000","text_align":"left","title_bottom_space":{"unit":"px","size":0,"sizes":[]},"title_typography_typography":"custom","title_typography_font_size":{"unit":"px","size":21,"sizes":[]},"title_typography_font_weight":"400","title_typography_line_height":{"unit":"em","size":0.1,"sizes":[]},"description_typography_font_size":{"unit":"px","size":14,"sizes":[]},"description_typography_line_height":{"unit":"em","size":1.5,"sizes":[]},"description_typography_letter_spacing":{"unit":"px","size":0.5,"sizes":[]},"_padding":{"unit":"px","top":"10","right":"10","bottom":"10","left":"10","isLinked":false}},"elements":[],"isInner":false,"widgetType":"icon-box","elType":"widget"}],"isInner":true,"elType":"column"},{"id":"73a83baa","settings":{"_column_size":33,"_inline_size":null},"elements":[{"id":"5a7163c0","settings":{"title_text":"Skype","description_text":"alberto_recoba","icon_size":{"unit":"px","size":48,"sizes":[]},"description_typography_typography":"custom","selected_icon":{"value":{"id":595,"url":"http:\/\/localhost\/wordpress-lawfirm\/wp-content\/uploads\/unlimited_elements\/skype.svg"},"library":"svg"},"title_size":"span","primary_color":"#000000","title_color":"#000000","text_align":"left","title_bottom_space":{"unit":"px","size":0,"sizes":[]},"title_typography_typography":"custom","title_typography_font_size":{"unit":"px","size":21,"sizes":[]},"title_typography_font_weight":"400","title_typography_line_height":{"unit":"em","size":0.1,"sizes":[]},"description_typography_font_size":{"unit":"px","size":14,"sizes":[]},"description_typography_line_height":{"unit":"em","size":1.5,"sizes":[]},"description_typography_letter_spacing":{"unit":"px","size":0.5,"sizes":[]},"_padding":{"unit":"px","top":"10","right":"10","bottom":"10","left":"10","isLinked":false}},"elements":[],"isInner":false,"widgetType":"icon-box","elType":"widget"}],"isInner":true,"elType":"column"},{"id":"67602fe0","settings":{"_column_size":33,"_inline_size":null},"elements":[{"id":"3c425ed4","settings":{"title_text":"Website","description_text":"www.akbertirecoa.com\n","icon_size":{"unit":"px","size":48,"sizes":[]},"description_typography_typography":"custom","selected_icon":{"value":{"id":596,"url":"http:\/\/localhost\/wordpress-lawfirm\/wp-content\/uploads\/unlimited_elements\/website.svg"},"library":"svg"},"title_size":"span","primary_color":"#000000","title_color":"#000000","text_align":"left","title_bottom_space":{"unit":"px","size":0,"sizes":[]},"title_typography_typography":"custom","title_typography_font_size":{"unit":"px","size":21,"sizes":[]},"title_typography_font_weight":"400","title_typography_line_height":{"unit":"em","size":0.1,"sizes":[]},"description_typography_font_size":{"unit":"px","size":14,"sizes":[]},"description_typography_line_height":{"unit":"em","size":1.5,"sizes":[]},"description_typography_letter_spacing":{"unit":"px","size":0.5,"sizes":[]},"_padding":{"unit":"px","top":"10","right":"10","bottom":"10","left":"10","isLinked":false}},"elements":[],"isInner":false,"widgetType":"icon-box","elType":"widget"}],"isInner":true,"elType":"column"}],"isInner":true,"elType":"section"}],"isInner":false,"elType":"column"}],"isInner":false,"elType":"section"},{"id":"6b5ee7f6","settings":{"stretch_section":"section-stretched","content_width":{"unit":"px","size":1170,"sizes":[]},"gap":"no"},"elements":[{"id":"6e6c8170","settings":{"_column_size":100,"_inline_size":null},"elements":[{"id":"1e73600a","settings":[],"elements":[],"isInner":false,"widgetType":"spacer","elType":"widget"},{"id":"6f105752","settings":{"text":"Divider","color":"#E0E0E0"},"elements":[],"isInner":false,"widgetType":"divider","elType":"widget"},{"id":"13767f0a","settings":[],"elements":[],"isInner":false,"widgetType":"spacer","elType":"widget"}],"isInner":false,"elType":"column"}],"isInner":false,"elType":"section"},{"id":"532acea8","settings":{"stretch_section":"section-stretched","content_width":{"unit":"px","size":1170,"sizes":[]},"gap":"no","animation":"slideInUp"},"elements":[{"id":"18ee9b35","settings":{"_column_size":100,"_inline_size":null,"padding":{"unit":"px","top":"20","right":"20","bottom":"20","left":"20","isLinked":true},"padding_tablet":{"unit":"px","top":"20","right":"20","bottom":"20","left":"20","isLinked":true}},"elements":[{"id":"2bc58a21","settings":{"title":"My Portfolio","size":"large","header_size":"span","title_color":"#000000","typography_typography":"custom","typography_font_weight":"400","_margin":{"unit":"px","top":"0","right":"0","bottom":"0","left":"0","isLinked":false},"_padding":{"unit":"px","top":"0","right":"0","bottom":"0","left":"0","isLinked":false}},"elements":[],"isInner":false,"widgetType":"heading","elType":"widget"},{"id":"4e83bd50","settings":{"width":{"unit":"%","size":5,"sizes":[]},"text":"Divider","color":"#A4BAD3","weight":{"unit":"px","size":5,"sizes":[]},"width_mobile":{"unit":"px","size":30,"sizes":[]}},"elements":[],"isInner":false,"widgetType":"divider","elType":"widget"}],"isInner":false,"elType":"column"}],"isInner":false,"elType":"section"},{"id":"2b6c750c","settings":{"stretch_section":"section-stretched","content_width":{"unit":"px","size":1170,"sizes":[]},"gap":"no","structure":"30","margin":{"unit":"%","top":"03","right":0,"bottom":"0","left":0,"isLinked":false},"animation":"slideInUp"},"elements":[{"id":"6bc88ddf","settings":{"_column_size":33,"_inline_size":null},"elements":[{"id":"56986ef2","settings":{"image_one":{"id":585,"url":"http:\/\/localhost\/wordpress-lawfirm\/wp-content\/uploads\/unlimited_elements\/cv_clean_gallery4.jpg"},"icon_one":{"value":"","library":""},"title_one":"T-Shirt Design","content_one":"Project Description","link_one":{"url":"","is_external":"","nofollow":"","custom_attributes":""},"color":"#000000","ucfont_content_one__fonts-enabled":"yes","ucfont_content_one__typography_typography":"custom"},"elements":[],"isInner":false,"widgetType":"ucaddon_solid_color_overlay_icon_box","elType":"widget"}],"isInner":false,"elType":"column"},{"id":"2775ab42","settings":{"_column_size":33,"_inline_size":null},"elements":[{"id":"37f597a5","settings":{"image_one":{"id":584,"url":"http:\/\/localhost\/wordpress-lawfirm\/wp-content\/uploads\/unlimited_elements\/cv_clean_gallery3.jpg"},"icon_one":{"value":"","library":""},"title_one":"Mobile App","content_one":"Project Description","link_one":{"url":"","is_external":"","nofollow":"","custom_attributes":""},"color":"#000000","ucfont_content_one__fonts-enabled":"yes","ucfont_content_one__typography_typography":"custom"},"elements":[],"isInner":false,"widgetType":"ucaddon_solid_color_overlay_icon_box","elType":"widget"}],"isInner":false,"elType":"column"},{"id":"783175c1","settings":{"_column_size":33,"_inline_size":null},"elements":[{"id":"8a2a414","settings":{"image_one":{"id":586,"url":"http:\/\/localhost\/wordpress-lawfirm\/wp-content\/uploads\/unlimited_elements\/cv_clean_gallery5.jpg"},"icon_one":{"value":"","library":""},"title_one":"Poster Design","content_one":"Project Description","link_one":{"url":"","is_external":"","nofollow":"","custom_attributes":""},"color":"#000000","ucfont_content_one__fonts-enabled":"yes","ucfont_content_one__typography_typography":"custom"},"elements":[],"isInner":false,"widgetType":"ucaddon_solid_color_overlay_icon_box","elType":"widget"}],"isInner":false,"elType":"column"}],"isInner":false,"elType":"section"},{"id":"442706d7","settings":{"stretch_section":"section-stretched","content_width":{"unit":"px","size":1170,"sizes":[]},"gap":"no","structure":"30"},"elements":[{"id":"35dee546","settings":{"_column_size":33,"_inline_size":null},"elements":[{"id":"6b7b6da5","settings":{"image_one":{"id":587,"url":"http:\/\/localhost\/wordpress-lawfirm\/wp-content\/uploads\/unlimited_elements\/cv_clean_gallery6.jpg"},"icon_one":{"value":"","library":""},"title_one":"Illustrations","content_one":"Project Description","link_one":{"url":"","is_external":"","nofollow":"","custom_attributes":""},"color":"#000000","ucfont_content_one__fonts-enabled":"yes","ucfont_content_one__typography_typography":"custom"},"elements":[],"isInner":false,"widgetType":"ucaddon_solid_color_overlay_icon_box","elType":"widget"}],"isInner":false,"elType":"column"},{"id":"10a7cff9","settings":{"_column_size":33,"_inline_size":null},"elements":[{"id":"1095fa17","settings":{"image_one":{"id":588,"url":"http:\/\/localhost\/wordpress-lawfirm\/wp-content\/uploads\/unlimited_elements\/cv_clean_gallery7.jpg"},"icon_one":{"value":"","library":""},"title_one":"Product Design","content_one":"Project Description","link_one":{"url":"","is_external":"","nofollow":"","custom_attributes":""},"color":"#000000","ucfont_content_one__fonts-enabled":"yes","ucfont_content_one__typography_typography":"custom"},"elements":[],"isInner":false,"widgetType":"ucaddon_solid_color_overlay_icon_box","elType":"widget"}],"isInner":false,"elType":"column"},{"id":"10cf2349","settings":{"_column_size":33,"_inline_size":null},"elements":[{"id":"27b0d9d9","settings":{"image_one":{"id":583,"url":"http:\/\/localhost\/wordpress-lawfirm\/wp-content\/uploads\/unlimited_elements\/cv_clean_gallery2.jpg"},"icon_one":{"value":"","library":""},"title_one":"Application Design","content_one":"Project Description","link_one":{"url":"","is_external":"","nofollow":"","custom_attributes":""},"color":"#000000","ucfont_content_one__fonts-enabled":"yes","ucfont_content_one__typography_typography":"custom"},"elements":[],"isInner":false,"widgetType":"ucaddon_solid_color_overlay_icon_box","elType":"widget"}],"isInner":false,"elType":"column"}],"isInner":false,"elType":"section"},{"id":"75478c0e","settings":{"stretch_section":"section-stretched","layout":"full_width"},"elements":[{"id":"1875d257","settings":{"_column_size":100,"_inline_size":null},"elements":[{"id":"6ccc7098","settings":[],"elements":[],"isInner":false,"widgetType":"spacer","elType":"widget"}],"isInner":false,"elType":"column"}],"isInner":false,"elType":"section"},{"id":"5a0d7e59","settings":{"stretch_section":"section-stretched","content_width":{"unit":"px","size":1170,"sizes":[]},"structure":"21","gap":"no","animation":"slideInUp"},"elements":[{"id":"37982282","settings":{"_column_size":33,"_inline_size":null,"padding":{"unit":"px","top":"20","right":"20","bottom":"20","left":"20","isLinked":true},"padding_tablet":{"unit":"px","top":"20","right":"20","bottom":"20","left":"20","isLinked":true}},"elements":[{"id":"7971cb81","settings":{"title":"My Experience","size":"large","header_size":"span","title_color":"#000000","typography_typography":"custom","typography_font_weight":"400"},"elements":[],"isInner":false,"widgetType":"heading","elType":"widget"},{"id":"2a9b4c93","settings":{"width":{"unit":"%","size":10,"sizes":[]},"text":"Divider","color":"#A4BAD3","weight":{"unit":"px","size":5,"sizes":[]},"width_mobile":{"unit":"px","size":30,"sizes":[]}},"elements":[],"isInner":false,"widgetType":"divider","elType":"widget"}],"isInner":false,"elType":"column"},{"id":"7636baa9","settings":{"_column_size":66,"_inline_size":null,"margin_mobile":{"unit":"px","top":"0","right":"0","bottom":"0","left":"0","isLinked":true},"padding_mobile":{"unit":"px","top":"20","right":"20","bottom":"20","left":"20","isLinked":true}},"elements":[{"id":"4fe01e84","settings":{"dot_color":"#A4BAD3","uc_items":[{"title":"Art Director - Facebook Inc.","description":"Rerum si librem pssimus amet excepturi Exercitationem enim dolores sunt prasentium dolurum Exercitationem enim dolores sunt prasentium dolurum","date":"Present","title_company":"","item_repeater_class":"elementor-repeater-item-","_id":"197a3b1"},{"title":"Web Designer - Google Inc","description":"Rerum si librem pssimus amet excepturi Exercitationem enim dolores sunt prasentium dolurum Exercitationem enim dolores sunt prasentium dolurum ","date":"2012 - 2016","title_company":"","item_repeater_class":"elementor-repeater-item-","_id":"d17ba33"},{"title":"Senior Developer - Abc Inc","description":"Rerum si librem pssimus amet excepturi Exercitationem enim dolores sunt prasentium dolurum Exercitationem enim dolores sunt prasentium dolurum ","date":"2010 - 2012","title_company":"","item_repeater_class":"elementor-repeater-item-","_id":"7a16476"},{"title":"Internship - Abc","description":"Rerum si librem pssimus amet excepturi Exercitationem enim dolores sunt prasentium dolurum Exercitationem enim dolores sunt prasentium dolurum ","date":"2009 - 2010","title_company":"","item_repeater_class":"elementor-repeater-item-","_id":"5ad701e"}],"ucfont_uc_items_attribute_title__fonts-enabled":"yes","ucfont_uc_items_attribute_description__fonts-enabled":"yes","ucfont_uc_items_attribute_date__fonts-enabled":"yes","ucfont_uc_items_attribute_date__typography_typography":"custom","ucfont_uc_items_attribute_date__typography_font_size":{"unit":"px","size":14,"sizes":[]},"ucfont_uc_items_attribute_date__typography_font_weight":"600","ucfont_uc_items_attribute_date__color":"#8FA0A3"},"elements":[],"isInner":false,"widgetType":"ucaddon_blox_cv_timeline","elType":"widget"}],"isInner":false,"elType":"column"}],"isInner":false,"elType":"section"},{"id":"33df4bf4","settings":{"stretch_section":"section-stretched","content_width":{"unit":"px","size":1170,"sizes":[]},"gap":"no"},"elements":[{"id":"3f30a390","settings":{"_column_size":100,"_inline_size":null},"elements":[{"id":"1dcd658b","settings":[],"elements":[],"isInner":false,"widgetType":"spacer","elType":"widget"},{"id":"4c9c18f2","settings":{"text":"Divider","color":"#E0E0E0"},"elements":[],"isInner":false,"widgetType":"divider","elType":"widget"},{"id":"1e17ae42","settings":[],"elements":[],"isInner":false,"widgetType":"spacer","elType":"widget"}],"isInner":false,"elType":"column"}],"isInner":false,"elType":"section"},{"id":"1dea37fe","settings":{"stretch_section":"section-stretched","content_width":{"unit":"px","size":1170,"sizes":[]},"structure":"21","gap":"no","animation":"slideInUp"},"elements":[{"id":"5c386fcd","settings":{"_column_size":33,"_inline_size":null,"padding":{"unit":"px","top":"20","right":"20","bottom":"20","left":"20","isLinked":true},"padding_tablet":{"unit":"px","top":"20","right":"20","bottom":"20","left":"20","isLinked":true}},"elements":[{"id":"25d051b1","settings":{"title":"My Skills\n","size":"large","header_size":"span","title_color":"#000000","typography_typography":"custom","typography_font_weight":"400"},"elements":[],"isInner":false,"widgetType":"heading","elType":"widget"},{"id":"196b24e7","settings":{"width":{"unit":"%","size":10,"sizes":[]},"text":"Divider","color":"#A4BAD3","weight":{"unit":"px","size":5,"sizes":[]}},"elements":[],"isInner":false,"widgetType":"divider","elType":"widget"}],"isInner":false,"elType":"column"},{"id":"260d1a8","settings":{"_column_size":66,"_inline_size":null,"padding_mobile":{"unit":"px","top":"20","right":"20","bottom":"20","left":"20","isLinked":true}},"elements":[{"id":"7b673400","settings":{"title":"Web Development","color":"#A4BAD3","border_color":"#FFFFFF","amount":90,"speed":10,"top_border":1,"bar_height":6,"border_radius":0,"padding":0,"ucfont_title__fonts-enabled":"yes","ucfont_title__typography_typography":"custom","ucfont_title__typography_font_size":{"unit":"px","size":21,"sizes":[]}},"elements":[],"isInner":false,"widgetType":"ucaddon_linear_progress_bar","elType":"widget"},{"id":"3f8ee391","settings":{"title":"Graphic Design","color":"#A4BAD3","border_color":"#FFFFFF","amount":65,"speed":10,"top_border":1,"bar_height":6,"border_radius":0,"padding":0,"ucfont_title__fonts-enabled":"yes","ucfont_title__typography_typography":"custom","ucfont_title__typography_font_size":{"unit":"px","size":21,"sizes":[]}},"elements":[],"isInner":false,"widgetType":"ucaddon_linear_progress_bar","elType":"widget"},{"id":"5554dc70","settings":{"title":"User Experience","color":"#A4BAD3","border_color":"#FFFFFF","amount":75,"speed":10,"top_border":1,"bar_height":6,"border_radius":0,"padding":0,"ucfont_title__fonts-enabled":"yes","ucfont_title__typography_typography":"custom","ucfont_title__typography_font_size":{"unit":"px","size":21,"sizes":[]}},"elements":[],"isInner":false,"widgetType":"ucaddon_linear_progress_bar","elType":"widget"},{"id":"2ca27b97","settings":{"title":"UI Design","color":"#A4BAD3","border_color":"#FFFFFF","amount":55,"speed":10,"top_border":1,"bar_height":6,"border_radius":0,"padding":0,"ucfont_title__fonts-enabled":"yes","ucfont_title__typography_typography":"custom","ucfont_title__typography_font_size":{"unit":"px","size":21,"sizes":[]}},"elements":[],"isInner":false,"widgetType":"ucaddon_linear_progress_bar","elType":"widget"}],"isInner":false,"elType":"column"}],"isInner":false,"elType":"section"},{"id":"577f5f1b","settings":{"stretch_section":"section-stretched","content_width":{"unit":"px","size":1170,"sizes":[]},"gap":"no"},"elements":[{"id":"49da9f82","settings":{"_column_size":100,"_inline_size":null},"elements":[{"id":"2a177955","settings":[],"elements":[],"isInner":false,"widgetType":"spacer","elType":"widget"},{"id":"41aee4e8","settings":{"text":"Divider","color":"#E0E0E0"},"elements":[],"isInner":false,"widgetType":"divider","elType":"widget"},{"id":"347d04e","settings":[],"elements":[],"isInner":false,"widgetType":"spacer","elType":"widget"}],"isInner":false,"elType":"column"}],"isInner":false,"elType":"section"},{"id":"ca8357a","settings":{"stretch_section":"section-stretched","content_width":{"unit":"px","size":1170,"sizes":[]},"gap":"no","structure":"21","_element_id":"contact","animation":"slideInUp"},"elements":[{"id":"2345e1f2","settings":{"_column_size":33,"_inline_size":null,"padding":{"unit":"px","top":"20","right":"20","bottom":"20","left":"20","isLinked":true},"padding_tablet":{"unit":"px","top":"20","right":"20","bottom":"20","left":"20","isLinked":true}},"elements":[{"id":"4c4d1a1a","settings":{"title":"Get In Touch","size":"large","header_size":"span","title_color":"#000000","typography_typography":"custom","typography_font_weight":"400"},"elements":[],"isInner":false,"widgetType":"heading","elType":"widget"},{"id":"20a4b4f3","settings":{"width":{"unit":"%","size":10,"sizes":[]},"text":"Divider","color":"#A4BAD3","weight":{"unit":"px","size":5,"sizes":[]},"width_mobile":{"unit":"px","size":30,"sizes":[]}},"elements":[],"isInner":false,"widgetType":"divider","elType":"widget"}],"isInner":false,"elType":"column"},{"id":"172ef713","settings":{"_column_size":66,"_inline_size":null},"elements":[{"id":"62cb1980","settings":{"address":"Potts Point","zoom":{"unit":"px","size":12,"sizes":[]},"height":{"unit":"px","size":500,"sizes":[]},"css_filters_css_filter":"custom","css_filters_saturate":{"unit":"px","size":4,"sizes":[]}},"elements":[],"isInner":false,"widgetType":"google_maps","elType":"widget"}],"isInner":false,"elType":"column"}],"isInner":false,"elType":"section"}]}